{
  "name": "Yard",	
	"longDesc": "\nYou are in the YARD.\nA hatch to the BASEMENT LAB is on the corner of the house,\nand a door to the DINING ROOM is on the side.\nYou can also step onto the FRONT PORCH from here.\nAn eagle flies overhead. Don't make eye contact with it if you don't want it to notice you!",
	"description": "\nYou are in the YARD.\nFrom here you can reach the BASEMENT LAB, DINING ROOM, and FRONT PORCH.",
	"items": {
		"eagle": {
			"name": "eagle",
			"description": "There is an eagle overhead.",
			"tooBig": true,
			"isFeature": true,
			"discovered": true,
			"containsHiddenObject": false,
			"discoveryStatement": "",
			"hiddenObject": ""
		},
		"sandbox": {
			"name": "sandbox",
			"description": "There is a sandbox full of beach toys and buckets.",
			"tooBig": true,
			"isFeature": true,
			"discovered": true,
			"containsHiddenObject": true,
			"discoveryStatement": "There's lots of SAND in here too.",
			"hiddenObject": "sand"
		},
		"sand": {
			"name": "sand",
			"description": "The sand is a uniform light brown.",
			"tooBig": false,
			"isFeature": false,
			"discovered": false,
			"containsHiddenObject": false,
			"discoveryStatement": "",
			"hiddenObject": ""
		}
	},
	"visited" : false,
  "exits": [ "Basement Lab", "Dining Room", "Front Porch" ]
}
